influx_logging_handler/__init__.py
influx_logging_handler/handlers.py
influx_logging_handler/utils.py
influx_logging_handler-0.3.1.dist-info/LICENSE
influx_logging_handler-0.3.1.dist-info/METADATA
influx_logging_handler-0.3.1.dist-info/WHEEL
influx_logging_handler-0.3.1.dist-info/top_level.txt
influx_logging_handler-0.3.1.dist-info/RECORD
