Metadata-Version: 2.1
Name: influx-logging-handler
Version: 0.3.1
Summary: Handler for logging messages to InfluxDB 2 via Python logging -module.
Home-page: https://gitlab.com/kipe/influx_logging_handler/
Author: Kimmo Huoman
Author-email: kipenroskaposti+influx_logging_handler@gmail.com
License: MIT
Platform: UNKNOWN
Requires-Python: >=3.7
License-File: LICENSE
Requires-Dist: influxdb-client (>=1.24.0)
